{
  "parent": "minecraft:recipes/root",
  "criteria": {
    "has_pulse_leggings": {
      "conditions": {
        "items": [
          {
            "items": [
              "skulkatum:pulse_leggings"
            ]
          }
        ]
      },
      "trigger": "minecraft:inventory_changed"
    },
    "has_the_recipe": {
      "conditions": {
        "recipe": "skulkatum:pulse_leggings"
      },
      "trigger": "minecraft:recipe_unlocked"
    }
  },
  "requirements": [
    [
      "has_pulse_leggings",
      "has_the_recipe"
    ]
  ],
  "rewards": {
    "recipes": [
      "skulkatum:pulse_leggings"
    ]
  },
  "sends_telemetry_event": false
}